{
  "$schema": "https://typedoc.org/schema.json",
  "entryPoints": ["./src/index.ts"],
  "out": "./docs",
  "tsconfig": "./tsconfig.app.json",
  "name": "@astralarium/pixi-three",
  "readme": "./README.md",
  "includeVersion": true,
  "excludePrivate": true,
  "excludeProtected": false,
  "excludeInternal": true,
  "excludeExternals": true,
  "categoryOrder": ["component", "hook", "*"],
  "navigation": {
    "includeCategories": true
  },
  "navigationLinks": {
    "GitHub": "https://github.com/astralarium/pixi-three"
  },
  "plugin": ["typedoc-rhineai-theme"]
}
